LICENSE
MANIFEST.in
README.rst
pyproject.toml
setup.cfg
setup.py
django_react_templates.egg-info/PKG-INFO
django_react_templates.egg-info/SOURCES.txt
django_react_templates.egg-info/dependency_links.txt
django_react_templates.egg-info/requires.txt
django_react_templates.egg-info/top_level.txt
react_templates/__init__.py
react_templates/admin.py
react_templates/apps.py
react_templates/render.py
react_templates/tests.py
react_templates/wsgi.py
react_templates/core/__init__.py
react_templates/core/check.py
react_templates/core/install.py
react_templates/core/log.py
react_templates/core/regex.py
react_templates/migrations/__init__.py
react_templates/templates/_django_react_templates/base.html