Metadata-Version: 2.1
Name: django-react-templates
Version: 0.1
Summary: A Django app that allows React templating.
Home-page: https://github.com/brenodega28/django-reactive
Author: Breno Gomes
Author-email: brenodega28@gmail.com
License: MIT  # Example license
Classifier: Environment :: Web Environment
Classifier: Framework :: Django
Classifier: Intended Audience :: Developers
Classifier: Operating System :: OS Independent
Classifier: Programming Language :: Python
Classifier: Programming Language :: Python :: 3
Classifier: Topic :: Internet :: WWW/HTTP
Classifier: Topic :: Internet :: WWW/HTTP :: Dynamic Content
Requires-Python: >=3.8
License-File: LICENSE
